[{"paymentRecordId":1,"merchantId":1,"success":false,"payment":{"creditCardNumber":"374596806171083","expiryMonth":"2","expiryYear":"21","amount":24.0,"currency":"EUR","cardIssuer":"VISA","cvv":"863"}},{"paymentRecordId":2,"merchantId":2,"success":true,"payment":{"creditCardNumber":"340847739148917","expiryMonth":"11","expiryYear":"12","amount":167.0,"currency":"GBP","cardIssuer":"VISA","cvv":"526"}},{"paymentRecordId":3,"merchantId":3,"success":false,"payment":{"creditCardNumber":"2515394249907404","expiryMonth":"10","expiryYear":"16","amount":740.0,"currency":"USD","cardIssuer":"VISA","cvv":"560"}},{"paymentRecordId":4,"merchantId":3,"success":true,"payment":{"creditCardNumber":"346715150327217","expiryMonth":"2","expiryYear":"11","amount":635.0,"currency":"GBP","cardIssuer":"VISA","cvv":"841"}},{"paymentRecordId":5,"merchantId":1,"success":false,"payment":{"creditCardNumber":"377905317792724","expiryMonth":"2","expiryYear":"19","amount":31.0,"currency":"USD","cardIssuer":"VISA","cvv":"395"}},{"paymentRecordId":6,"merchantId":2,"success":true,"payment":{"creditCardNumber":"349981858960892","expiryMonth":"4","expiryYear":"22","amount":467.0,"currency":"EUR","cardIssuer":"VISA","cvv":"948"}},{"paymentRecordId":7,"merchantId":2,"success":false,"payment":{"creditCardNumber":"4414994293479","expiryMonth":"1","expiryYear":"15","amount":764.0,"currency":"EUR","cardIssuer":"VISA","cvv":"301"}},{"paymentRecordId":8,"merchantId":4,"success":true,"payment":{"creditCardNumber":"2539236368450439","expiryMonth":"11","expiryYear":"18","amount":68.0,"currency":"AUD","cardIssuer":"VISA","cvv":"416"}},{"paymentRecordId":9,"merchantId":3,"success":false,"payment":{"creditCardNumber":"4156058377736","expiryMonth":"1","expiryYear":"15","amount":418.0,"currency":"AUD","cardIssuer":"VISA","cvv":"617"}},{"paymentRecordId":10,"merchantId":4,"success":true,"payment":{"creditCardNumber":"2308804645210386","expiryMonth":"5","expiryYear":"20","amount":571.0,"currency":"AUD","cardIssuer":"VISA","cvv":"709"}},{"paymentRecordId":11,"merchantId":2,"success":false,"payment":{"creditCardNumber":"2418078797814363","expiryMonth":"9","expiryYear":"15","amount":808.0,"currency":"GBP","cardIssuer":"VISA","cvv":"255"}},{"paymentRecordId":12,"merchantId":3,"success":true,"payment":{"creditCardNumber":"349244199846233","expiryMonth":"9","expiryYear":"11","amount":508.0,"currency":"USD","cardIssuer":"VISA","cvv":"409"}},{"paymentRecordId":13,"merchantId":1,"success":false,"payment":{"creditCardNumber":"4273667498546","expiryMonth":"7","expiryYear":"11","amount":428.0,"currency":"AUD","cardIssuer":"VISA","cvv":"332"}},{"paymentRecordId":14,"merchantId":1,"success":true,"payment":{"creditCardNumber":"2483413399890372","expiryMonth":"3","expiryYear":"24","amount":580.0,"currency":"USD","cardIssuer":"VISA","cvv":"317"}},{"paymentRecordId":15,"merchantId":4,"success":false,"payment":{"creditCardNumber":"342472504764349","expiryMonth":"6","expiryYear":"13","amount":739.0,"currency":"AUD","cardIssuer":"VISA","cvv":"905"}},{"paymentRecordId":16,"merchantId":1,"success":true,"payment":{"creditCardNumber":"340383557758645","expiryMonth":"1","expiryYear":"24","amount":242.0,"currency":"EUR","cardIssuer":"VISA","cvv":"312"}},{"paymentRecordId":17,"merchantId":2,"success":false,"payment":{"creditCardNumber":"2221461945503707","expiryMonth":"6","expiryYear":"10","amount":973.0,"currency":"USD","cardIssuer":"VISA","cvv":"279"}},{"paymentRecordId":18,"merchantId":4,"success":true,"payment":{"creditCardNumber":"2549627973053808","expiryMonth":"1","expiryYear":"21","amount":309.0,"currency":"GBP","cardIssuer":"VISA","cvv":"969"}},{"paymentRecordId":19,"merchantId":1,"success":false,"payment":{"creditCardNumber":"2382764372905005","expiryMonth":"6","expiryYear":"24","amount":895.0,"currency":"USD","cardIssuer":"VISA","cvv":"169"}},{"paymentRecordId":20,"merchantId":2,"success":true,"payment":{"creditCardNumber":"4108037811251","expiryMonth":"4","expiryYear":"16","amount":162.0,"currency":"GBP","cardIssuer":"VISA","cvv":"661"}},{"paymentRecordId":21,"merchantId":3,"success":false,"payment":{"creditCardNumber":"2668739247111299","expiryMonth":"4","expiryYear":"20","amount":677.0,"currency":"EUR","cardIssuer":"VISA","cvv":"170"}},{"paymentRecordId":22,"merchantId":2,"success":true,"payment":{"creditCardNumber":"4476987892542","expiryMonth":"9","expiryYear":"15","amount":56.0,"currency":"AUD","cardIssuer":"VISA","cvv":"440"}},{"paymentRecordId":23,"merchantId":3,"success":false,"payment":{"creditCardNumber":"2418307451915830","expiryMonth":"8","expiryYear":"11","amount":961.0,"currency":"AUD","cardIssuer":"VISA","cvv":"466"}},{"paymentRecordId":24,"merchantId":1,"success":true,"payment":{"creditCardNumber":"2605480821338323","expiryMonth":"3","expiryYear":"24","amount":982.0,"currency":"GBP","cardIssuer":"VISA","cvv":"513"}},{"paymentRecordId":25,"merchantId":1,"success":false,"payment":{"creditCardNumber":"4519506447445","expiryMonth":"1","expiryYear":"14","amount":68.0,"currency":"AUD","cardIssuer":"VISA","cvv":"625"}},{"paymentRecordId":26,"merchantId":2,"success":true,"payment":{"creditCardNumber":"342031153040771","expiryMonth":"7","expiryYear":"11","amount":665.0,"currency":"GBP","cardIssuer":"VISA","cvv":"354"}},{"paymentRecordId":27,"merchantId":1,"success":false,"payment":{"creditCardNumber":"4885261296826","expiryMonth":"4","expiryYear":"14","amount":59.0,"currency":"GBP","cardIssuer":"VISA","cvv":"679"}},{"paymentRecordId":28,"merchantId":2,"success":true,"payment":{"creditCardNumber":"2585987451365222","expiryMonth":"5","expiryYear":"16","amount":385.0,"currency":"EUR","cardIssuer":"VISA","cvv":"191"}},{"paymentRecordId":29,"merchantId":4,"success":false,"payment":{"creditCardNumber":"2587545839766384","expiryMonth":"11","expiryYear":"23","amount":39.0,"currency":"GBP","cardIssuer":"VISA","cvv":"944"}},{"paymentRecordId":30,"merchantId":1,"success":true,"payment":{"creditCardNumber":"4918835339507","expiryMonth":"5","expiryYear":"13","amount":968.0,"currency":"AUD","cardIssuer":"VISA","cvv":"621"}},{"paymentRecordId":31,"merchantId":3,"success":false,"payment":{"creditCardNumber":"2628798100175949","expiryMonth":"8","expiryYear":"13","amount":113.0,"currency":"EUR","cardIssuer":"VISA","cvv":"288"}},{"paymentRecordId":32,"merchantId":3,"success":true,"payment":{"creditCardNumber":"4311960694120","expiryMonth":"3","expiryYear":"24","amount":367.0,"currency":"USD","cardIssuer":"VISA","cvv":"374"}},{"paymentRecordId":33,"merchantId":2,"success":false,"payment":{"creditCardNumber":"341251210209463","expiryMonth":"6","expiryYear":"24","amount":69.0,"currency":"USD","cardIssuer":"VISA","cvv":"802"}},{"paymentRecordId":34,"merchantId":3,"success":true,"payment":{"creditCardNumber":"341275635390608","expiryMonth":"3","expiryYear":"15","amount":399.0,"currency":"USD","cardIssuer":"VISA","cvv":"817"}},{"paymentRecordId":35,"merchantId":1,"success":false,"payment":{"creditCardNumber":"4162838180804","expiryMonth":"7","expiryYear":"20","amount":963.0,"currency":"EUR","cardIssuer":"VISA","cvv":"859"}},{"paymentRecordId":36,"merchantId":2,"success":true,"payment":{"creditCardNumber":"4509354877843","expiryMonth":"1","expiryYear":"14","amount":973.0,"currency":"USD","cardIssuer":"VISA","cvv":"144"}},{"paymentRecordId":37,"merchantId":1,"success":false,"payment":{"creditCardNumber":"370186860034742","expiryMonth":"8","expiryYear":"15","amount":834.0,"currency":"EUR","cardIssuer":"VISA","cvv":"563"}},{"paymentRecordId":38,"merchantId":4,"success":true,"payment":{"creditCardNumber":"2703069248992647","expiryMonth":"1","expiryYear":"13","amount":136.0,"currency":"USD","cardIssuer":"VISA","cvv":"856"}},{"paymentRecordId":39,"merchantId":3,"success":false,"payment":{"creditCardNumber":"4795286953311","expiryMonth":"10","expiryYear":"24","amount":152.0,"currency":"AUD","cardIssuer":"VISA","cvv":"759"}},{"paymentRecordId":40,"merchantId":2,"success":true,"payment":{"creditCardNumber":"2471400767771031","expiryMonth":"6","expiryYear":"20","amount":641.0,"currency":"GBP","cardIssuer":"VISA","cvv":"278"}},{"paymentRecordId":41,"merchantId":3,"success":false,"payment":{"creditCardNumber":"2360437845817794","expiryMonth":"7","expiryYear":"19","amount":478.0,"currency":"GBP","cardIssuer":"VISA","cvv":"279"}},{"paymentRecordId":42,"merchantId":1,"success":true,"payment":{"creditCardNumber":"4007581776425","expiryMonth":"6","expiryYear":"13","amount":432.0,"currency":"GBP","cardIssuer":"VISA","cvv":"596"}},{"paymentRecordId":43,"merchantId":3,"success":false,"payment":{"creditCardNumber":"2530264465173885","expiryMonth":"10","expiryYear":"14","amount":203.0,"currency":"EUR","cardIssuer":"VISA","cvv":"301"}},{"paymentRecordId":44,"merchantId":3,"success":true,"payment":{"creditCardNumber":"2645123601697995","expiryMonth":"8","expiryYear":"18","amount":224.0,"currency":"EUR","cardIssuer":"VISA","cvv":"822"}},{"paymentRecordId":45,"merchantId":4,"success":false,"payment":{"creditCardNumber":"4071124013217","expiryMonth":"10","expiryYear":"16","amount":765.0,"currency":"AUD","cardIssuer":"VISA","cvv":"986"}},{"paymentRecordId":46,"merchantId":2,"success":true,"payment":{"creditCardNumber":"341012477324878","expiryMonth":"1","expiryYear":"13","amount":946.0,"currency":"AUD","cardIssuer":"VISA","cvv":"143"}},{"paymentRecordId":47,"merchantId":2,"success":false,"payment":{"creditCardNumber":"4486819131969","expiryMonth":"9","expiryYear":"19","amount":234.0,"currency":"EUR","cardIssuer":"VISA","cvv":"176"}},{"paymentRecordId":48,"merchantId":2,"success":true,"payment":{"creditCardNumber":"345189217796346","expiryMonth":"6","expiryYear":"12","amount":169.0,"currency":"EUR","cardIssuer":"VISA","cvv":"584"}},{"paymentRecordId":49,"merchantId":2,"success":false,"payment":{"creditCardNumber":"4074367381366","expiryMonth":"10","expiryYear":"13","amount":195.0,"currency":"GBP","cardIssuer":"VISA","cvv":"659"}},{"paymentRecordId":50,"merchantId":4,"success":true,"payment":{"creditCardNumber":"4018413939586","expiryMonth":"5","expiryYear":"22","amount":443.0,"currency":"AUD","cardIssuer":"VISA","cvv":"911"}},{"paymentRecordId":51,"merchantId":1,"success":false,"payment":{"creditCardNumber":"2342447596903100","expiryMonth":"11","expiryYear":"16","amount":285.0,"currency":"USD","cardIssuer":"VISA","cvv":"175"}},{"paymentRecordId":52,"merchantId":1,"success":true,"payment":{"creditCardNumber":"4460031873021","expiryMonth":"5","expiryYear":"12","amount":585.0,"currency":"GBP","cardIssuer":"VISA","cvv":"271"}},{"paymentRecordId":53,"merchantId":3,"success":false,"payment":{"creditCardNumber":"348534179119580","expiryMonth":"6","expiryYear":"10","amount":956.0,"currency":"USD","cardIssuer":"VISA","cvv":"693"}},{"paymentRecordId":54,"merchantId":1,"success":true,"payment":{"creditCardNumber":"4486496362051","expiryMonth":"11","expiryYear":"17","amount":936.0,"currency":"GBP","cardIssuer":"VISA","cvv":"876"}},{"paymentRecordId":55,"merchantId":2,"success":false,"payment":{"creditCardNumber":"345187555227023","expiryMonth":"9","expiryYear":"14","amount":355.0,"currency":"USD","cardIssuer":"VISA","cvv":"350"}},{"paymentRecordId":56,"merchantId":3,"success":true,"payment":{"creditCardNumber":"2597592808162417","expiryMonth":"10","expiryYear":"14","amount":402.0,"currency":"EUR","cardIssuer":"VISA","cvv":"702"}},{"paymentRecordId":57,"merchantId":1,"success":false,"payment":{"creditCardNumber":"4504205339325","expiryMonth":"7","expiryYear":"11","amount":118.0,"currency":"USD","cardIssuer":"VISA","cvv":"112"}},{"paymentRecordId":58,"merchantId":3,"success":true,"payment":{"creditCardNumber":"2472842596038786","expiryMonth":"7","expiryYear":"15","amount":383.0,"currency":"GBP","cardIssuer":"VISA","cvv":"151"}},{"paymentRecordId":59,"merchantId":3,"success":false,"payment":{"creditCardNumber":"4337925111702","expiryMonth":"5","expiryYear":"22","amount":973.0,"currency":"AUD","cardIssuer":"VISA","cvv":"753"}},{"paymentRecordId":60,"merchantId":4,"success":true,"payment":{"creditCardNumber":"377809737149798","expiryMonth":"5","expiryYear":"14","amount":22.0,"currency":"GBP","cardIssuer":"VISA","cvv":"963"}},{"paymentRecordId":61,"merchantId":1,"success":false,"payment":{"creditCardNumber":"379166083934598","expiryMonth":"7","expiryYear":"22","amount":695.0,"currency":"USD","cardIssuer":"VISA","cvv":"621"}},{"paymentRecordId":62,"merchantId":2,"success":true,"payment":{"creditCardNumber":"4403194746378","expiryMonth":"10","expiryYear":"20","amount":507.0,"currency":"GBP","cardIssuer":"VISA","cvv":"300"}},{"paymentRecordId":63,"merchantId":3,"success":false,"payment":{"creditCardNumber":"4757316214460","expiryMonth":"10","expiryYear":"17","amount":68.0,"currency":"GBP","cardIssuer":"VISA","cvv":"756"}},{"paymentRecordId":64,"merchantId":3,"success":true,"payment":{"creditCardNumber":"2342370640181418","expiryMonth":"5","expiryYear":"19","amount":35.0,"currency":"AUD","cardIssuer":"VISA","cvv":"604"}},{"paymentRecordId":65,"merchantId":1,"success":false,"payment":{"creditCardNumber":"2418050256329084","expiryMonth":"2","expiryYear":"12","amount":264.0,"currency":"AUD","cardIssuer":"VISA","cvv":"357"}},{"paymentRecordId":66,"merchantId":3,"success":true,"payment":{"creditCardNumber":"4708647188568","expiryMonth":"7","expiryYear":"17","amount":599.0,"currency":"USD","cardIssuer":"VISA","cvv":"203"}},{"paymentRecordId":67,"merchantId":1,"success":false,"payment":{"creditCardNumber":"4113018396306","expiryMonth":"11","expiryYear":"17","amount":299.0,"currency":"USD","cardIssuer":"VISA","cvv":"611"}},{"paymentRecordId":68,"merchantId":3,"success":true,"payment":{"creditCardNumber":"371912777303931","expiryMonth":"5","expiryYear":"17","amount":794.0,"currency":"GBP","cardIssuer":"VISA","cvv":"682"}},{"paymentRecordId":69,"merchantId":1,"success":false,"payment":{"creditCardNumber":"4757084681700","expiryMonth":"2","expiryYear":"22","amount":264.0,"currency":"GBP","cardIssuer":"VISA","cvv":"595"}},{"paymentRecordId":70,"merchantId":3,"success":true,"payment":{"creditCardNumber":"341868001101573","expiryMonth":"8","expiryYear":"21","amount":767.0,"currency":"USD","cardIssuer":"VISA","cvv":"620"}},{"paymentRecordId":71,"merchantId":1,"success":false,"payment":{"creditCardNumber":"4770412098463","expiryMonth":"6","expiryYear":"17","amount":80.0,"currency":"AUD","cardIssuer":"VISA","cvv":"120"}},{"paymentRecordId":72,"merchantId":2,"success":true,"payment":{"creditCardNumber":"4309105950407","expiryMonth":"11","expiryYear":"20","amount":198.0,"currency":"USD","cardIssuer":"VISA","cvv":"359"}},{"paymentRecordId":73,"merchantId":3,"success":false,"payment":{"creditCardNumber":"2287259359495779","expiryMonth":"8","expiryYear":"14","amount":638.0,"currency":"USD","cardIssuer":"VISA","cvv":"332"}},{"paymentRecordId":74,"merchantId":2,"success":true,"payment":{"creditCardNumber":"345098354425991","expiryMonth":"9","expiryYear":"10","amount":228.0,"currency":"AUD","cardIssuer":"VISA","cvv":"751"}},{"paymentRecordId":75,"merchantId":2,"success":false,"payment":{"creditCardNumber":"4639857477773","expiryMonth":"8","expiryYear":"14","amount":557.0,"currency":"USD","cardIssuer":"VISA","cvv":"307"}},{"paymentRecordId":76,"merchantId":4,"success":true,"payment":{"creditCardNumber":"371635451066967","expiryMonth":"6","expiryYear":"13","amount":234.0,"currency":"GBP","cardIssuer":"VISA","cvv":"657"}},{"paymentRecordId":77,"merchantId":2,"success":false,"payment":{"creditCardNumber":"4523408485974","expiryMonth":"3","expiryYear":"24","amount":221.0,"currency":"GBP","cardIssuer":"VISA","cvv":"884"}},{"paymentRecordId":78,"merchantId":2,"success":true,"payment":{"creditCardNumber":"374044025591518","expiryMonth":"6","expiryYear":"13","amount":555.0,"currency":"AUD","cardIssuer":"VISA","cvv":"965"}},{"paymentRecordId":79,"merchantId":3,"success":false,"payment":{"creditCardNumber":"4809737574996","expiryMonth":"10","expiryYear":"16","amount":818.0,"currency":"USD","cardIssuer":"VISA","cvv":"822"}},{"paymentRecordId":80,"merchantId":3,"success":true,"payment":{"creditCardNumber":"4547606115810","expiryMonth":"9","expiryYear":"10","amount":93.0,"currency":"USD","cardIssuer":"VISA","cvv":"228"}},{"paymentRecordId":81,"merchantId":1,"success":false,"payment":{"creditCardNumber":"343991577908888","expiryMonth":"10","expiryYear":"20","amount":684.0,"currency":"USD","cardIssuer":"VISA","cvv":"979"}},{"paymentRecordId":82,"merchantId":4,"success":true,"payment":{"creditCardNumber":"2447073210132126","expiryMonth":"1","expiryYear":"21","amount":711.0,"currency":"USD","cardIssuer":"VISA","cvv":"358"}},{"paymentRecordId":83,"merchantId":1,"success":false,"payment":{"creditCardNumber":"5471566596424159","expiryMonth":"11","expiryYear":"11","amount":153.0,"currency":"GBP","cardIssuer":"VISA","cvv":"436"}},{"paymentRecordId":84,"merchantId":2,"success":true,"payment":{"creditCardNumber":"4681780508381","expiryMonth":"1","expiryYear":"24","amount":180.0,"currency":"AUD","cardIssuer":"VISA","cvv":"237"}},{"paymentRecordId":85,"merchantId":2,"success":false,"payment":{"creditCardNumber":"341280704646393","expiryMonth":"7","expiryYear":"21","amount":890.0,"currency":"GBP","cardIssuer":"VISA","cvv":"906"}},{"paymentRecordId":86,"merchantId":3,"success":true,"payment":{"creditCardNumber":"378491868599817","expiryMonth":"7","expiryYear":"14","amount":135.0,"currency":"EUR","cardIssuer":"VISA","cvv":"292"}},{"paymentRecordId":87,"merchantId":3,"success":false,"payment":{"creditCardNumber":"349641755196673","expiryMonth":"6","expiryYear":"15","amount":6.0,"currency":"EUR","cardIssuer":"VISA","cvv":"394"}},{"paymentRecordId":88,"merchantId":4,"success":true,"payment":{"creditCardNumber":"2225278058374346","expiryMonth":"10","expiryYear":"15","amount":327.0,"currency":"GBP","cardIssuer":"VISA","cvv":"919"}},{"paymentRecordId":89,"merchantId":3,"success":false,"payment":{"creditCardNumber":"343989072122807","expiryMonth":"5","expiryYear":"21","amount":102.0,"currency":"AUD","cardIssuer":"VISA","cvv":"954"}},{"paymentRecordId":90,"merchantId":2,"success":true,"payment":{"creditCardNumber":"4400034324457","expiryMonth":"11","expiryYear":"14","amount":523.0,"currency":"USD","cardIssuer":"VISA","cvv":"713"}},{"paymentRecordId":91,"merchantId":2,"success":false,"payment":{"creditCardNumber":"2527818702864963","expiryMonth":"1","expiryYear":"16","amount":975.0,"currency":"GBP","cardIssuer":"VISA","cvv":"939"}},{"paymentRecordId":92,"merchantId":4,"success":true,"payment":{"creditCardNumber":"4676349075237","expiryMonth":"9","expiryYear":"20","amount":275.0,"currency":"AUD","cardIssuer":"VISA","cvv":"233"}},{"paymentRecordId":93,"merchantId":3,"success":false,"payment":{"creditCardNumber":"343903305211097","expiryMonth":"10","expiryYear":"13","amount":519.0,"currency":"USD","cardIssuer":"VISA","cvv":"220"}},{"paymentRecordId":94,"merchantId":3,"success":true,"payment":{"creditCardNumber":"346042635617702","expiryMonth":"4","expiryYear":"24","amount":902.0,"currency":"AUD","cardIssuer":"VISA","cvv":"503"}},{"paymentRecordId":95,"merchantId":2,"success":false,"payment":{"creditCardNumber":"2680659570481222","expiryMonth":"2","expiryYear":"15","amount":51.0,"currency":"GBP","cardIssuer":"VISA","cvv":"705"}},{"paymentRecordId":96,"merchantId":2,"success":true,"payment":{"creditCardNumber":"375074511705099","expiryMonth":"10","expiryYear":"13","amount":718.0,"currency":"EUR","cardIssuer":"VISA","cvv":"636"}},{"paymentRecordId":97,"merchantId":4,"success":false,"payment":{"creditCardNumber":"373728472199111","expiryMonth":"4","expiryYear":"17","amount":5.0,"currency":"GBP","cardIssuer":"VISA","cvv":"892"}},{"paymentRecordId":98,"merchantId":4,"success":true,"payment":{"creditCardNumber":"345678343003304","expiryMonth":"2","expiryYear":"23","amount":730.0,"currency":"GBP","cardIssuer":"VISA","cvv":"181"}},{"paymentRecordId":99,"merchantId":2,"success":false,"payment":{"creditCardNumber":"373831708314023","expiryMonth":"2","expiryYear":"19","amount":729.0,"currency":"AUD","cardIssuer":"VISA","cvv":"763"}},{"paymentRecordId":100,"merchantId":3,"success":true,"payment":{"creditCardNumber":"2589667443345104","expiryMonth":"11","expiryYear":"17","amount":673.0,"currency":"AUD","cardIssuer":"VISA","cvv":"873"}}]